textprepper/__init__.py
textprepper/base.py
textprepper/modifiers.py
textprepper/removers.py
textprepper-0.0.2.dist-info/LICENSE
textprepper-0.0.2.dist-info/METADATA
textprepper-0.0.2.dist-info/WHEEL
textprepper-0.0.2.dist-info/RECORD
