Metadata-Version: 2.1
Name: textprepper
Version: 0.0.2
Summary: TextPrepper is a simple text preprocessing tool designed to modify queries and documents for Langchain applications.
Home-page: https://github.com/RySE-AI/TextPrepper
License: Apache-2.0
Author: RySE-AI
Author-email: Ryo.Shibata@outlook.de
Requires-Python: >=3.9,<4.0
Classifier: Development Status :: 3 - Alpha
Classifier: License :: OSI Approved :: Apache Software License
Classifier: Natural Language :: English
Classifier: Programming Language :: Python :: 3
Classifier: Programming Language :: Python :: 3.9
Classifier: Programming Language :: Python :: 3.10
Classifier: Programming Language :: Python :: 3.11
Classifier: Programming Language :: Python :: 3.12
Requires-Dist: deep-translator (>=1.11.0,<2.0.0)
Requires-Dist: langchain-core (==0.*)
Requires-Dist: nltk (>=3.6.7,<4.0.0)
Requires-Dist: pydantic (>=2.6.1,<3.0.0)
Requires-Dist: pyspellchecker (>=0.8.0,<0.9.0)
Project-URL: Repository, https://github.com/RySE-AI/TextPrepper
